muse_data_parser.py
muse_discovery.py
muse_discovery_gui.py
muse_exact_client.py
muse_fnirs_processor.py
muse_integrated_parser.py
muse_ppg_heart_rate.py
muse_raw_stream.py
muse_realtime_decoder.py
muse_replay.py
muse_sleep_client.py
muse_sleep_parser.py
muse_stream_client.py
muse_visualizer.py
amused-1.0.2.dist-info/LICENSE
amused-1.0.2.dist-info/METADATA
amused-1.0.2.dist-info/WHEEL
amused-1.0.2.dist-info/top_level.txt
amused-1.0.2.dist-info/RECORD
