Metadata-Version: 2.2
Name: amused
Version: 1.0.2
Summary: Open-source Python library for streaming data from Muse S (Athena) EEG headbands
Author-email: Adrian Tadeusz Belmans <adrian.belmans@gmail.com>
License: MIT
Project-URL: Homepage, https://github.com/nexon33/amused
Project-URL: Documentation, https://github.com/nexon33/amused#readme
Project-URL: Repository, https://github.com/nexon33/amused
Project-URL: Issues, https://github.com/nexon33/amused/issues
Keywords: muse,eeg,ppg,fnirs,biometrics,neuroscience,brain-computer-interface,bci,bluetooth,ble,biosignals,heart-rate,meditation,sleep-monitoring
Classifier: Development Status :: 4 - Beta
Classifier: Intended Audience :: Developers
Classifier: Intended Audience :: Science/Research
Classifier: Operating System :: OS Independent
Classifier: Programming Language :: Python :: 3
Classifier: Programming Language :: Python :: 3.8
Classifier: Programming Language :: Python :: 3.9
Classifier: Programming Language :: Python :: 3.10
Classifier: Programming Language :: Python :: 3.11
Classifier: Programming Language :: Python :: 3.12
Classifier: Topic :: Scientific/Engineering :: Medical Science Apps.
Classifier: Topic :: Scientific/Engineering :: Information Analysis
Classifier: Topic :: Software Development :: Libraries :: Python Modules
Requires-Python: >=3.8
License-File: LICENSE
Requires-Dist: bleak>=0.21.0
Requires-Dist: numpy>=1.20.0
Requires-Dist: scipy>=1.7.0
Requires-Dist: pandas>=1.3.0
Provides-Extra: dev
Requires-Dist: pytest>=7.0; extra == "dev"
Requires-Dist: pytest-asyncio>=0.21.0; extra == "dev"
Requires-Dist: pytest-cov>=4.0; extra == "dev"
Requires-Dist: black>=23.0; extra == "dev"
Requires-Dist: flake8>=6.0; extra == "dev"
Requires-Dist: mypy>=1.0; extra == "dev"
Provides-Extra: docs
Requires-Dist: sphinx>=6.0; extra == "docs"
Requires-Dist: sphinx-rtd-theme>=1.2; extra == "docs"
Requires-Dist: sphinx-autodoc-typehints>=1.22; extra == "docs"
